Metadata-Version: 1.0
Name: wordDistance
Version: 0.1.2
Summary: word distance wrapper for log analysis
Home-page: UNKNOWN
Author: Rui Ren
Author-email: UNKNOWN
License: UNKNOWN
Platform: UNKNOWN
